positions_backtester/__init__.py
positions_backtester/_previous_execution.py
positions_backtester/backtester.py
positions_backtester/logger.py
positions_backtester/simple_execution.py
positions_backtester-0.1.5.dist-info/LICENSE.txt
positions_backtester-0.1.5.dist-info/WHEEL
positions_backtester-0.1.5.dist-info/METADATA
positions_backtester-0.1.5.dist-info/RECORD
