Metadata-Version: 2.1
Name: positions-backtester
Version: 0.1.5
Summary: Package to backtest trading strategies (dataframe with positions) with execution costs modeling
Home-page: https://github.com/stas-prokopiev/positions_backtester
License: MIT
Author: stanislav
Author-email: stas.prokopiev@gmail.com
Requires-Python: >=3.7,<4.0
Classifier: License :: OSI Approved :: MIT License
Classifier: Programming Language :: Python :: 3
Classifier: Programming Language :: Python :: 3.10
Classifier: Programming Language :: Python :: 3.7
Classifier: Programming Language :: Python :: 3.8
Classifier: Programming Language :: Python :: 3.9
Requires-Dist: pandas (>=1.4.0,<2.0.0)
Requires-Dist: tqdm (>=4.64.0,<5.0.0)
Project-URL: Repository, https://github.com/stas-prokopiev/positions_backtester
